unet_stylegan2/__init__.py
unet_stylegan2/diff_augment.py
unet_stylegan2/unet_stylegan2.py
unet_stylegan2-0.5.1.data/scripts/unet_stylegan2
unet_stylegan2-0.5.1.dist-info/LICENSE
unet_stylegan2-0.5.1.dist-info/METADATA
unet_stylegan2-0.5.1.dist-info/WHEEL
unet_stylegan2-0.5.1.dist-info/top_level.txt
unet_stylegan2-0.5.1.dist-info/RECORD
