Metadata-Version: 2.1
Name: unet-stylegan2
Version: 0.5.1
Summary: StyleGan2 with UNet Discriminator, in Pytorch
Home-page: https://github.com/lucidrains/unet-stylegan2
Author: Phil Wang
Author-email: lucidrains@gmail.com
License: GPLv3+
Keywords: generative adversarial networks,artificial intelligence
Platform: UNKNOWN
Classifier: Development Status :: 4 - Beta
Classifier: Intended Audience :: Developers
Classifier: Topic :: Scientific/Engineering :: Artificial Intelligence
Classifier: License :: OSI Approved :: MIT License
Classifier: Programming Language :: Python :: 3.6
Requires-Dist: fire
Requires-Dist: numpy
Requires-Dist: retry
Requires-Dist: tqdm
Requires-Dist: torch
Requires-Dist: torchvision
Requires-Dist: pillow
Requires-Dist: linear-attention-transformer (>=0.12.1)
